{"_ts":[1530424628,1530466129],"_r":{"breakdown":{"html":{"bytes":[380673,380696],"requests":[6,6]},"js":{"bytes":[76625,76595],"requests":[16,16]},"css":{"bytes":[43706,43692],"requests":[7,7]},"image":{"bytes":[76795,76788],"requests":[5,5]},"flash":{"bytes":[0,0],"requests":[0,0]},"font":{"bytes":[0,0],"requests":[0,0]},"video":{"bytes":[0,0],"requests":[0,0]},"other":{"bytes":[0,0],"requests":[0,0]}},"date":[1530424628,1530466129],"domElements":[2144,2144],"domInteractive":[698,684],"firstPaint":[609.5999999998,592.3999999941],"fullyLoaded":[2281,2265],"id":["180701_C3_2fb68a540bc9bccfe0a447d544ebaf4d","180701_3S_ce891aa44fc06da7c346d9b8f812d03c"],"loadTime":[1533,1530],"render":[600,600],"SpeedIndex":[1012,1021],"TTFB":[478,468],"videoFrames":[[{"_i":"ms_000000.jpg","_t":0,"_vc":0},{"_i":"ms_000600.jpg","_t":600,"_vc":31},{"_i":"ms_000800.jpg","_t":800,"_vc":32},{"_i":"ms_000900.jpg","_t":900,"_vc":32},{"_i":"ms_001000.jpg","_t":1000,"_vc":37},{"_i":"ms_001200.jpg","_t":1200,"_vc":94},{"_i":"ms_001300.jpg","_t":1300,"_vc":94},{"_i":"ms_001400.jpg","_t":1400,"_vc":100}],[{"_i":"ms_000000.jpg","_t":0,"_vc":0},{"_i":"ms_000600.jpg","_t":600,"_vc":31},{"_i":"ms_000800.jpg","_t":800,"_vc":31},{"_i":"ms_000900.jpg","_t":900,"_vc":32},{"_i":"ms_001000.jpg","_t":1000,"_vc":36},{"_i":"ms_001100.jpg","_t":1100,"_vc":37},{"_i":"ms_001200.jpg","_t":1200,"_vc":93},{"_i":"ms_001300.jpg","_t":1300,"_vc":94},{"_i":"ms_001400.jpg","_t":1400,"_vc":94},{"_i":"ms_001500.jpg","_t":1500,"_vc":100}]],"visualComplete":[1400,1500],"lighthouse":[100,100],"pagespeed":[100,100]}}